toml_env_conf/__init__.py
toml_env_conf/loader.py
toml_env_conf-0.1.3.dist-info/WHEEL
toml_env_conf-0.1.3.dist-info/METADATA
toml_env_conf-0.1.3.dist-info/RECORD
